Workbook

Sheet Read me
A1: Time-and-cost validation workbook
A3: Why: 108 services are released to sell by quote then invoice, but none has measured economics. This workbook records real jobs so the 50% floor is tested on facts.
A4: Labor rate: DEC-LABOR-001 (owner-approved 2026-09-01), Tier 1 $60, Tier 2 $75, Tier 3 $100 per hour. These are internal cost rates, not wages, retail prices or provider payouts; owner draw is separate.
A5: Log: one row per paid job. Use a reference, never a client name. Take hours from a timer or calendar, and the fee from the processor record.
A6: Include acquisition cost (lead fees, ads) for the job. It is a real cost; the only measured job so far lost about 26% of revenue to it.
A7: A row counts as MEASURED only when hours come from a timer and the fee from a processor record. Estimates are PARTIAL and never verify anything.
A8: This file never changes Production. Any decision to reprice, rescope or mark a service verified belongs to the owner.

Sheet Targets
A1: Services under validation (prices from Production; hours are DRAFT estimates until validated)
A3: SKU | B3: Service | C3: Locked price | D3: Tier | E3: Rate (DEC-LABOR-001) | F3: Draft hours | G3: Max hours at 50% floor | H3: Draft margin | I3: Status
A4: DNI-04A-001 | B4: Virtual Assistant | C4: 149 | D4: 2 | E4: =IF(D4=1,60,IF(D4=2,75,100)) | F4: 1 | G4: =ROUND(((1-0.5-0.029)*C4)/E4,2) | H4: =(C4-F4*E4-0.029*C4)/C4 | I4: ECONOMICALLY_UNVERIFIED
A5: DNI-04A-007 | B5: Document Formatting | C5: 139 | D5: 2 | E5: =IF(D5=1,60,IF(D5=2,75,100)) | F5: 1 | G5: =ROUND(((1-0.5-0.029)*C5)/E5,2) | H5: =(C5-F5*E5-0.029*C5)/C5 | I5: ECONOMICALLY_UNVERIFIED
A6: DNI-04A-009 | B6: Research Assistant | C6: 225 | D6: 3 | E6: =IF(D6=1,60,IF(D6=2,75,100)) | F6: 1.5 | G6: =ROUND(((1-0.5-0.029)*C6)/E6,2) | H6: =(C6-F6*E6-0.029*C6)/C6 | I6: ECONOMICALLY_UNVERIFIED
A7: DNI-04A-010 | B7: Project Coordination | C7: 275 | D7: 3 | E7: =IF(D7=1,60,IF(D7=2,75,100)) | F7: 1.5 | G7: =ROUND(((1-0.5-0.029)*C7)/E7,2) | H7: =(C7-F7*E7-0.029*C7)/C7 | I7: ECONOMICALLY_UNVERIFIED
A8: DNI-04A-008 | B8: Meeting Support | C8: 225 | D8: 2 | E8: =IF(D8=1,60,IF(D8=2,75,100)) | F8: 1.5 | G8: =ROUND(((1-0.5-0.029)*C8)/E8,2) | H8: =(C8-F8*E8-0.029*C8)/C8 | I8: ECONOMICALLY_UNVERIFIED
A10: Floor and fee assumptions
A11: Margin floor | B11: 0.5
A12: Processing fee used in the draft column | B12: 0.029
A13: In the Job log, enter the ACTUAL processor fee from the payout record, not this assumption.

Sheet Job log
A1: Job date | B1: SKU | C1: Job reference (no names or private data) | D1: Collected (USD) | E1: Actual processor fee (USD) | F1: Hours: intake and scoping | G1: Hours: delivery | H1: Hours: QA and revisions | I1: Hours: admin and follow-up | J1: Other direct cost (USD) | K1: Acquisition cost (USD) | L1: Hours source (timer / calendar / estimate) | M1: Fee source (processor record / estimate) | N1: Total hours | O1: Rate | P1: Labor cost | Q1: Total cost | R1: Contribution | S1: Margin | T1: Clears 50%? | U1: Evidence
N2: =IF(B2="","",SUM(F2:I2)) | O2: =IF(B2="","",IFERROR(INDEX(Targets!$E$4:$E$8,MATCH(B2,Targets!$A$4:$A$8,0)),"SKU?")) | P2: =IF(B2="","",IFERROR(N2*O2,"")) | Q2: =IF(B2="","",IFERROR(P2+E2+J2+K2,"")) | R2: =IF(B2="","",IFERROR(D2-Q2,"")) | S2: =IF(B2="","",IFERROR(IF(D2>0,R2/D2,""),"")) | T2: =IF(S2="","",IF(S2>=Targets!$B$11,"YES","NO")) | U2: =IF(B2="","",IF(AND(L2="timer",M2="processor record"),"MEASURED","PARTIAL"))
N3: =IF(B3="","",SUM(F3:I3)) | O3: =IF(B3="","",IFERROR(INDEX(Targets!$E$4:$E$8,MATCH(B3,Targets!$A$4:$A$8,0)),"SKU?")) | P3: =IF(B3="","",IFERROR(N3*O3,"")) | Q3: =IF(B3="","",IFERROR(P3+E3+J3+K3,"")) | R3: =IF(B3="","",IFERROR(D3-Q3,"")) | S3: =IF(B3="","",IFERROR(IF(D3>0,R3/D3,""),"")) | T3: =IF(S3="","",IF(S3>=Targets!$B$11,"YES","NO")) | U3: =IF(B3="","",IF(AND(L3="timer",M3="processor record"),"MEASURED","PARTIAL"))
N4: =IF(B4="","",SUM(F4:I4)) | O4: =IF(B4="","",IFERROR(INDEX(Targets!$E$4:$E$8,MATCH(B4,Targets!$A$4:$A$8,0)),"SKU?")) | P4: =IF(B4="","",IFERROR(N4*O4,"")) | Q4: =IF(B4="","",IFERROR(P4+E4+J4+K4,"")) | R4: =IF(B4="","",IFERROR(D4-Q4,"")) | S4: =IF(B4="","",IFERROR(IF(D4>0,R4/D4,""),"")) | T4: =IF(S4="","",IF(S4>=Targets!$B$11,"YES","NO")) | U4: =IF(B4="","",IF(AND(L4="timer",M4="processor record"),"MEASURED","PARTIAL"))
N5: =IF(B5="","",SUM(F5:I5)) | O5: =IF(B5="","",IFERROR(INDEX(Targets!$E$4:$E$8,MATCH(B5,Targets!$A$4:$A$8,0)),"SKU?")) | P5: =IF(B5="","",IFERROR(N5*O5,"")) | Q5: =IF(B5="","",IFERROR(P5+E5+J5+K5,"")) | R5: =IF(B5="","",IFERROR(D5-Q5,"")) | S5: =IF(B5="","",IFERROR(IF(D5>0,R5/D5,""),"")) | T5: =IF(S5="","",IF(S5>=Targets!$B$11,"YES","NO")) | U5: =IF(B5="","",IF(AND(L5="timer",M5="processor record"),"MEASURED","PARTIAL"))
N6: =IF(B6="","",SUM(F6:I6)) | O6: =IF(B6="","",IFERROR(INDEX(Targets!$E$4:$E$8,MATCH(B6,Targets!$A$4:$A$8,0)),"SKU?")) | P6: =IF(B6="","",IFERROR(N6*O6,"")) | Q6: =IF(B6="","",IFERROR(P6+E6+J6+K6,"")) | R6: =IF(B6="","",IFERROR(D6-Q6,"")) | S6: =IF(B6="","",IFERROR(IF(D6>0,R6/D6,""),"")) | T6: =IF(S6="","",IF(S6>=Targets!$B$11,"YES","NO")) | U6: =IF(B6="","",IF(AND(L6="timer",M6="processor record"),"MEASURED","PARTIAL"))
N7: =IF(B7="","",SUM(F7:I7)) | O7: =IF(B7="","",IFERROR(INDEX(Targets!$E$4:$E$8,MATCH(B7,Targets!$A$4:$A$8,0)),"SKU?")) | P7: =IF(B7="","",IFERROR(N7*O7,"")) | Q7: =IF(B7="","",IFERROR(P7+E7+J7+K7,"")) | R7: =IF(B7="","",IFERROR(D7-Q7,"")) | S7: =IF(B7="","",IFERROR(IF(D7>0,R7/D7,""),"")) | T7: =IF(S7="","",IF(S7>=Targets!$B$11,"YES","NO")) | U7: =IF(B7="","",IF(AND(L7="timer",M7="processor record"),"MEASURED","PARTIAL"))
N8: =IF(B8="","",SUM(F8:I8)) | O8: =IF(B8="","",IFERROR(INDEX(Targets!$E$4:$E$8,MATCH(B8,Targets!$A$4:$A$8,0)),"SKU?")) | P8: =IF(B8="","",IFERROR(N8*O8,"")) | Q8: =IF(B8="","",IFERROR(P8+E8+J8+K8,"")) | R8: =IF(B8="","",IFERROR(D8-Q8,"")) | S8: =IF(B8="","",IFERROR(IF(D8>0,R8/D8,""),"")) | T8: =IF(S8="","",IF(S8>=Targets!$B$11,"YES","NO")) | U8: =IF(B8="","",IF(AND(L8="timer",M8="processor record"),"MEASURED","PARTIAL"))
N9: =IF(B9="","",SUM(F9:I9)) | O9: =IF(B9="","",IFERROR(INDEX(Targets!$E$4:$E$8,MATCH(B9,Targets!$A$4:$A$8,0)),"SKU?")) | P9: =IF(B9="","",IFERROR(N9*O9,"")) | Q9: =IF(B9="","",IFERROR(P9+E9+J9+K9,"")) | R9: =IF(B9="","",IFERROR(D9-Q9,"")) | S9: =IF(B9="","",IFERROR(IF(D9>0,R9/D9,""),"")) | T9: =IF(S9="","",IF(S9>=Targets!$B$11,"YES","NO")) | U9: =IF(B9="","",IF(AND(L9="timer",M9="processor record"),"MEASURED","PARTIAL"))
N10: =IF(B10="","",SUM(F10:I10)) | O10: =IF(B10="","",IFERROR(INDEX(Targets!$E$4:$E$8,MATCH(B10,Targets!$A$4:$A$8,0)),"SKU?")) | P10: =IF(B10="","",IFERROR(N10*O10,"")) | Q10: =IF(B10="","",IFERROR(P10+E10+J10+K10,"")) | R10: =IF(B10="","",IFERROR(D10-Q10,"")) | S10: =IF(B10="","",IFERROR(IF(D10>0,R10/D10,""),"")) | T10: =IF(S10="","",IF(S10>=Targets!$B$11,"YES","NO")) | U10: =IF(B10="","",IF(AND(L10="timer",M10="processor record"),"MEASURED","PARTIAL"))
N11: =IF(B11="","",SUM(F11:I11)) | O11: =IF(B11="","",IFERROR(INDEX(Targets!$E$4:$E$8,MATCH(B11,Targets!$A$4:$A$8,0)),"SKU?")) | P11: =IF(B11="","",IFERROR(N11*O11,"")) | Q11: =IF(B11="","",IFERROR(P11+E11+J11+K11,"")) | R11: =IF(B11="","",IFERROR(D11-Q11,"")) | S11: =IF(B11="","",IFERROR(IF(D11>0,R11/D11,""),"")) | T11: =IF(S11="","",IF(S11>=Targets!$B$11,"YES","NO")) | U11: =IF(B11="","",IF(AND(L11="timer",M11="processor record"),"MEASURED","PARTIAL"))
N12: =IF(B12="","",SUM(F12:I12)) | O12: =IF(B12="","",IFERROR(INDEX(Targets!$E$4:$E$8,MATCH(B12,Targets!$A$4:$A$8,0)),"SKU?")) | P12: =IF(B12="","",IFERROR(N12*O12,"")) | Q12: =IF(B12="","",IFERROR(P12+E12+J12+K12,"")) | R12: =IF(B12="","",IFERROR(D12-Q12,"")) | S12: =IF(B12="","",IFERROR(IF(D12>0,R12/D12,""),"")) | T12: =IF(S12="","",IF(S12>=Targets!$B$11,"YES","NO")) | U12: =IF(B12="","",IF(AND(L12="timer",M12="processor record"),"MEASURED","PARTIAL"))
N13: =IF(B13="","",SUM(F13:I13)) | O13: =IF(B13="","",IFERROR(INDEX(Targets!$E$4:$E$8,MATCH(B13,Targets!$A$4:$A$8,0)),"SKU?")) | P13: =IF(B13="","",IFERROR(N13*O13,"")) | Q13: =IF(B13="","",IFERROR(P13+E13+J13+K13,"")) | R13: =IF(B13="","",IFERROR(D13-Q13,"")) | S13: =IF(B13="","",IFERROR(IF(D13>0,R13/D13,""),"")) | T13: =IF(S13="","",IF(S13>=Targets!$B$11,"YES","NO")) | U13: =IF(B13="","",IF(AND(L13="timer",M13="processor record"),"MEASURED","PARTIAL"))
... N201: =IF(B201="","",SUM(F201:I201)) | O201: =IF(B201="","",IFERROR(INDEX(Targets!$E$4:$E$8,MATCH(B201,Targets!$A$4:$A$8,0)),"SKU?")) | P201: =IF(B201="","",IFERROR(N201*O201,"")) | Q201: =IF(B201="","",IFERROR(P201+E201+J201+K201,"")) | R201: =IF(B201="","",IFERROR(D201-Q201,"")) | S201: =IF(B201="","",IFERROR(IF(D201>0,R201/D201,""),"")) | T201: =IF(S201="","",IF(S201>=Targets!$B$11,"YES","NO")) | U201: =IF(B201="","",IF(AND(L201="timer",M201="processor record"),"MEASURED","PARTIAL"))

Sheet Summary
A1: Per-service result (only MEASURED jobs count toward verification)
A3: SKU | B3: Service | C3: Measured jobs | D3: Average actual hours | E3: Average margin (measured) | F3: Worst margin | G3: Draft hours | H3: Verdict
A4: =Targets!A4 | B4: =Targets!B4 | C4: =COUNTIFS('Job log'!$B$2:$B$201,A4,'Job log'!$U$2:$U$201,"MEASURED") | D4: =IF(C4=0,"",AVERAGEIFS('Job log'!$N$2:$N$201,'Job log'!$B$2:$B$201,A4,'Job log'!$U$2:$U$201,"MEASURED")) | E4: =IF(C4=0,"",AVERAGEIFS('Job log'!$S$2:$S$201,'Job log'!$B$2:$B$201,A4,'Job log'!$U$2:$U$201,"MEASURED")) | F4: =IF(C4=0,"",_xlfn.MINIFS('Job log'!$S$2:$S$201,'Job log'!$B$2:$B$201,A4,'Job log'!$U$2:$U$201,"MEASURED")) | G4: =Targets!F4 | H4: =IF(C4<3,"NEEDS MORE MEASURED JOBS (3 minimum, proposed)",IF(AND(E4>=Targets!$B$11,F4>=Targets!$B$11-0.1),"CANDIDATE FOR OWNER VERIFICATION","BELOW FLOOR: PRICE, SCOPE OR FULFILLMENT REVIEW"))
A5: =Targets!A5 | B5: =Targets!B5 | C5: =COUNTIFS('Job log'!$B$2:$B$201,A5,'Job log'!$U$2:$U$201,"MEASURED") | D5: =IF(C5=0,"",AVERAGEIFS('Job log'!$N$2:$N$201,'Job log'!$B$2:$B$201,A5,'Job log'!$U$2:$U$201,"MEASURED")) | E5: =IF(C5=0,"",AVERAGEIFS('Job log'!$S$2:$S$201,'Job log'!$B$2:$B$201,A5,'Job log'!$U$2:$U$201,"MEASURED")) | F5: =IF(C5=0,"",_xlfn.MINIFS('Job log'!$S$2:$S$201,'Job log'!$B$2:$B$201,A5,'Job log'!$U$2:$U$201,"MEASURED")) | G5: =Targets!F5 | H5: =IF(C5<3,"NEEDS MORE MEASURED JOBS (3 minimum, proposed)",IF(AND(E5>=Targets!$B$11,F5>=Targets!$B$11-0.1),"CANDIDATE FOR OWNER VERIFICATION","BELOW FLOOR: PRICE, SCOPE OR FULFILLMENT REVIEW"))
A6: =Targets!A6 | B6: =Targets!B6 | C6: =COUNTIFS('Job log'!$B$2:$B$201,A6,'Job log'!$U$2:$U$201,"MEASURED") | D6: =IF(C6=0,"",AVERAGEIFS('Job log'!$N$2:$N$201,'Job log'!$B$2:$B$201,A6,'Job log'!$U$2:$U$201,"MEASURED")) | E6: =IF(C6=0,"",AVERAGEIFS('Job log'!$S$2:$S$201,'Job log'!$B$2:$B$201,A6,'Job log'!$U$2:$U$201,"MEASURED")) | F6: =IF(C6=0,"",_xlfn.MINIFS('Job log'!$S$2:$S$201,'Job log'!$B$2:$B$201,A6,'Job log'!$U$2:$U$201,"MEASURED")) | G6: =Targets!F6 | H6: =IF(C6<3,"NEEDS MORE MEASURED JOBS (3 minimum, proposed)",IF(AND(E6>=Targets!$B$11,F6>=Targets!$B$11-0.1),"CANDIDATE FOR OWNER VERIFICATION","BELOW FLOOR: PRICE, SCOPE OR FULFILLMENT REVIEW"))
A7: =Targets!A7 | B7: =Targets!B7 | C7: =COUNTIFS('Job log'!$B$2:$B$201,A7,'Job log'!$U$2:$U$201,"MEASURED") | D7: =IF(C7=0,"",AVERAGEIFS('Job log'!$N$2:$N$201,'Job log'!$B$2:$B$201,A7,'Job log'!$U$2:$U$201,"MEASURED")) | E7: =IF(C7=0,"",AVERAGEIFS('Job log'!$S$2:$S$201,'Job log'!$B$2:$B$201,A7,'Job log'!$U$2:$U$201,"MEASURED")) | F7: =IF(C7=0,"",_xlfn.MINIFS('Job log'!$S$2:$S$201,'Job log'!$B$2:$B$201,A7,'Job log'!$U$2:$U$201,"MEASURED")) | G7: =Targets!F7 | H7: =IF(C7<3,"NEEDS MORE MEASURED JOBS (3 minimum, proposed)",IF(AND(E7>=Targets!$B$11,F7>=Targets!$B$11-0.1),"CANDIDATE FOR OWNER VERIFICATION","BELOW FLOOR: PRICE, SCOPE OR FULFILLMENT REVIEW"))
A8: =Targets!A8 | B8: =Targets!B8 | C8: =COUNTIFS('Job log'!$B$2:$B$201,A8,'Job log'!$U$2:$U$201,"MEASURED") | D8: =IF(C8=0,"",AVERAGEIFS('Job log'!$N$2:$N$201,'Job log'!$B$2:$B$201,A8,'Job log'!$U$2:$U$201,"MEASURED")) | E8: =IF(C8=0,"",AVERAGEIFS('Job log'!$S$2:$S$201,'Job log'!$B$2:$B$201,A8,'Job log'!$U$2:$U$201,"MEASURED")) | F8: =IF(C8=0,"",_xlfn.MINIFS('Job log'!$S$2:$S$201,'Job log'!$B$2:$B$201,A8,'Job log'!$U$2:$U$201,"MEASURED")) | G8: =Targets!F8 | H8: =IF(C8<3,"NEEDS MORE MEASURED JOBS (3 minimum, proposed)",IF(AND(E8>=Targets!$B$11,F8>=Targets!$B$11-0.1),"CANDIDATE FOR OWNER VERIFICATION","BELOW FLOOR: PRICE, SCOPE OR FULFILLMENT REVIEW"))
A11: Rules (proposed, owner to approve): a service is not economically verified until at least 3 MEASURED jobs exist, average margin is at or above the 50% floor and no measured job is more than 10 points below it. A verdict here never changes a price, a gate, or LIVE_READY status; the owner records any verification decision.
